thangar/__init__.py
thangar/__main__.py
thangar/config.py
thangar/crud.py
thangar/database.py
thangar/models.py
thangar/schemas.py
thangar/telegram.py
thangar-0.1.3.dist-info/LICENSE
thangar-0.1.3.dist-info/METADATA
thangar-0.1.3.dist-info/WHEEL
thangar-0.1.3.dist-info/entry_points.txt
thangar-0.1.3.dist-info/top_level.txt
thangar-0.1.3.dist-info/RECORD
