Metadata-Version: 2.1
Name: thangar
Version: 0.1.3
Summary: UNKNOWN
Home-page: UNKNOWN
Author: Oskar Sharipov
Author-email: oskarsh@riseup.net
License: Apache License Version 2.0
Platform: UNKNOWN
Classifier: Programming Language :: Python :: 3
Classifier: License :: OSI Approved :: Apache Software License
Classifier: Operating System :: OS Independent
Classifier: Environment :: Console
Requires-Python: >=3.7
License-File: LICENSE
Requires-Dist: SQLAlchemy (==1.4.14)
Requires-Dist: pydantic (==1.8.1)
Requires-Dist: typer (==0.3.2)
Requires-Dist: rich (==10.1.0)
Requires-Dist: Telethon (==1.21.1)
Requires-Dist: hjson (==3.0.2)
